{
  "#b615be38-9ed0-481a-8e95-30aef9fd2bc1": {
    "type": "Annotation",
    "body": [
      {
        "type": "TextualBody",
        "purpose": "Transliteration",
        "value": "2(disz)"
      },
      {
        "type": "TextualBody",
        "value": "Character",
        "purpose": "tagging"
      }
    ],
    "target": {
      "source": "https://heidicon.ub.uni-heidelberg.de/iiif/2/1113854:578004/full/full/0/default.jpg",
      "selector": {
        "type": "SvgSelector",
        "value": "<svg><polygon points=\"43.63103485107422,76.46034240722656 158.94827270507812,73.95344543457031 153.93447875976562,195.53793334960938 54.912071228027344,195.53793334960938\"></polygon></svg>"
      }
    },
    "@context": "http://www.w3.org/ns/anno.jsonld",
    "id": "#b615be38-9ed0-481a-8e95-30aef9fd2bc1"
  },
  "#08678621-6f75-4731-a456-46c10369c49a": {
    "type": "Annotation",
    "body": [
      {
        "type": "TextualBody",
        "purpose": "Transliteration",
        "value": "tug2"
      },
      {
        "type": "TextualBody",
        "value": "Character",
        "purpose": "tagging"
      }
    ],
    "target": {
      "source": "https://heidicon.ub.uni-heidelberg.de/iiif/2/1113854:578004/full/full/0/default.jpg",
      "selector": {
        "type": "SvgSelector",
        "value": "<svg><polygon points=\"167.722412109375,48.884483337402344 281.78619384765625,47.63103485107422 278.02587890625,196.7913818359375 172.7362060546875,201.80517578125\"></polygon></svg>"
      }
    },
    "@context": "http://www.w3.org/ns/anno.jsonld",
    "id": "#08678621-6f75-4731-a456-46c10369c49a"
  },
  "#02ce7053-8fb0-4e94-9e07-2eed2c9979c3": {
    "type": "Annotation",
    "body": [
      {
        "type": "TextualBody",
        "purpose": "Transliteration",
        "value": "7(disz)"
      },
      {
        "type": "TextualBody",
        "value": "Character",
        "purpose": "tagging"
      }
    ],
    "target": {
      "source": "https://heidicon.ub.uni-heidelberg.de/iiif/2/1113854:578004/full/full/0/default.jpg",
      "selector": {
        "type": "SvgSelector",
        "value": "<svg><polygon points=\"447.24139404296875,206.8189697265625 572.586181640625,213.08621215820312 560.0517578125,373.527587890625 442.22760009765625,371.02069091796875\"></polygon></svg>"
      }
    },
    "@context": "http://www.w3.org/ns/anno.jsonld",
    "id": "#02ce7053-8fb0-4e94-9e07-2eed2c9979c3"
  },
  "#f7cc1d1b-bb00-47e7-ab4d-80b94341793a": {
    "type": "Annotation",
    "body": [
      {
        "type": "TextualBody",
        "purpose": "Transliteration",
        "value": "la2"
      },
      {
        "type": "TextualBody",
        "value": "Character",
        "purpose": "tagging"
      }
    ],
    "target": {
      "source": "https://heidicon.ub.uni-heidelberg.de/iiif/2/1113854:578004/full/full/0/default.jpg",
      "selector": {
        "type": "SvgSelector",
        "value": "<svg><polygon points=\"160.20172119140625,208.07241821289062 283.0396423339844,204.31207275390625 278.02587890625,330.91033935546875 160.20172119140625,339.6844787597656\"></polygon></svg>"
      }
    },
    "@context": "http://www.w3.org/ns/anno.jsonld",
    "id": "#f7cc1d1b-bb00-47e7-ab4d-80b94341793a"
  }
}