{
  "#b2ab225c-dacd-4d89-b723-78291be497db": {
    "type": "Annotation",
    "body": [
      {
        "type": "TextualBody",
        "purpose": "Transliteration",
        "value": "7(disz)"
      },
      {
        "type": "TextualBody",
        "value": "Character",
        "purpose": "tagging"
      }
    ],
    "target": {
      "source": "https://heidicon.ub.uni-heidelberg.de/iiif/2/1113259:577433/full/full/0/default.jpg",
      "selector": {
        "type": "SvgSelector",
        "value": "<svg><polygon points=\"87.67144775390625,410.1661071777344 231.68006896972656,404.0118713378906 231.68006896972656,525.8653564453125 86.44060516357422,536.9429321289062\"></polygon></svg>"
      }
    },
    "@context": "http://www.w3.org/ns/anno.jsonld",
    "id": "#b2ab225c-dacd-4d89-b723-78291be497db"
  },
  "#6765e89b-d3f5-450c-8ec7-9d305a118af7": {
    "type": "Annotation",
    "body": [
      {
        "type": "TextualBody",
        "purpose": "Transliteration",
        "value": "lu2"
      },
      {
        "type": "TextualBody",
        "value": "Character",
        "purpose": "tagging"
      }
    ],
    "target": {
      "source": "https://heidicon.ub.uni-heidelberg.de/iiif/2/1113259:577433/full/full/0/default.jpg",
      "selector": {
        "type": "SvgSelector",
        "value": "<svg><polygon points=\"250.14271545410156,396.6268310546875 463.07855224609375,392.9342956542969 463.07855224609375,487.7091979980469 243.98849487304688,500.01763916015625\"></polygon></svg>"
      }
    },
    "@context": "http://www.w3.org/ns/anno.jsonld",
    "id": "#6765e89b-d3f5-450c-8ec7-9d305a118af7"
  },
  "#576a6c6f-dab9-4ec0-8f5b-97a454f0427d": {
    "type": "Annotation",
    "body": [
      {
        "type": "TextualBody",
        "purpose": "Transliteration",
        "value": "dingir"
      },
      {
        "type": "TextualBody",
        "value": "Character",
        "purpose": "tagging"
      }
    ],
    "target": {
      "source": "https://heidicon.ub.uni-heidelberg.de/iiif/2/1113259:577433/full/full/0/default.jpg",
      "selector": {
        "type": "SvgSelector",
        "value": "<svg><polygon points=\"469.2327575683594,390.4726257324219 580.0086059570312,383.0875549316406 586.162841796875,485.2475280761719 470.4635925292969,487.7091979980469\"></polygon></svg>"
      }
    },
    "@context": "http://www.w3.org/ns/anno.jsonld",
    "id": "#576a6c6f-dab9-4ec0-8f5b-97a454f0427d"
  }
}