{
  "#cb4da4a9-a091-4d07-8fb5-4e981c7c769a": {
    "type": "Annotation",
    "body": [
      {
        "type": "TextualBody",
        "purpose": "Transliteration",
        "value": "arad2"
      },
      {
        "type": "TextualBody",
        "value": "Character",
        "purpose": "tagging"
      }
    ],
    "target": {
      "source": "https://heidicon.ub.uni-heidelberg.de/iiif/2/1125703:590047/full/full/0/default.jpg",
      "selector": {
        "type": "SvgSelector",
        "value": "<svg><polygon points=\"31.30488395690918,193.82327270507812 241.69424438476562,195.47987365722656 236.7244110107422,334.6350402832031 26.33505630493164,331.3218078613281\"></polygon></svg>"
      }
    },
    "@context": "http://www.w3.org/ns/anno.jsonld",
    "id": "#cb4da4a9-a091-4d07-8fb5-4e981c7c769a"
  },
  "#117b4d20-3108-4294-8d56-03f78f0d715f": {
    "type": "Annotation",
    "body": [
      {
        "type": "TextualBody",
        "purpose": "Transliteration",
        "dimensions": {
          "x": 767,
          "y": 1153
        },
        "value": "ba"
      },
      {
        "type": "TextualBody",
        "value": "Character",
        "purpose": "tagging"
      }
    ],
    "target": {
      "source": "https://heidicon.ub.uni-heidelberg.de/iiif/2/1125703:590047/full/full/0/default.jpg",
      "selector": {
        "type": "SvgSelector",
        "value": "<svg><polygon points=\"117.11724853515625,920.412109375 242.35690307617188,920.412109375 240.3689727783203,1043.663818359375 115.12931823730469,1027.7603759765625\"></polygon></svg>"
      }
    },
    "@context": "http://www.w3.org/ns/anno.jsonld",
    "id": "#117b4d20-3108-4294-8d56-03f78f0d715f"
  },
  "#c05af31d-f6c1-4524-8111-114233591993": {
    "type": "Annotation",
    "body": [
      {
        "type": "TextualBody",
        "purpose": "Transliteration",
        "dimensions": {
          "x": 767,
          "y": 1153
        },
        "value": "du11"
      },
      {
        "type": "TextualBody",
        "value": "Character",
        "purpose": "tagging"
      }
    ],
    "target": {
      "source": "https://heidicon.ub.uni-heidelberg.de/iiif/2/1125703:590047/full/full/0/default.jpg",
      "selector": {
        "type": "SvgSelector",
        "value": "<svg><polygon points=\"425.24658203125,926.3759155273438 691.6293334960938,908.4844970703125 709.5206909179688,1023.7844848632812 429.2224426269531,1041.6759033203125\"></polygon></svg>"
      }
    },
    "@context": "http://www.w3.org/ns/anno.jsonld",
    "id": "#c05af31d-f6c1-4524-8111-114233591993"
  },
  "#7f671286-2bfa-4b8d-9adb-f44f8a6d6ead": {
    "type": "Annotation",
    "body": [
      {
        "type": "TextualBody",
        "purpose": "Transliteration",
        "dimensions": {
          "x": 767,
          "y": 1153
        },
        "value": "ki"
      },
      {
        "type": "TextualBody",
        "value": "Character",
        "purpose": "tagging"
      }
    ],
    "target": {
      "source": "https://heidicon.ub.uni-heidelberg.de/iiif/2/1125703:590047/full/full/0/default.jpg",
      "selector": {
        "type": "SvgSelector",
        "value": "<svg><polygon points=\"27.660348892211914,658.0051879882812 164.8275909423828,658.0051879882812 168.80345153808594,789.2086181640625 29.64828109741211,791.1965942382812\"></polygon></svg>"
      }
    },
    "@context": "http://www.w3.org/ns/anno.jsonld",
    "id": "#7f671286-2bfa-4b8d-9adb-f44f8a6d6ead"
  },
  "#a594d25f-e423-45cc-94e9-c907d87f0e30": {
    "type": "Annotation",
    "body": [
      {
        "type": "TextualBody",
        "purpose": "Transliteration",
        "dimensions": {
          "x": 767,
          "y": 1153
        },
        "value": "gal"
      },
      {
        "type": "TextualBody",
        "value": "Character",
        "purpose": "tagging"
      }
    ],
    "target": {
      "source": "https://heidicon.ub.uni-heidelberg.de/iiif/2/1125703:590047/full/full/0/default.jpg",
      "selector": {
        "type": "SvgSelector",
        "value": "<svg><polygon points=\"490.8482971191406,256.443115234375 637.9552001953125,268.3706970214844 631.9913940429688,389.6344909667969 484.8844909667969,377.7069091796875\"></polygon></svg>"
      }
    },
    "@context": "http://www.w3.org/ns/anno.jsonld",
    "id": "#a594d25f-e423-45cc-94e9-c907d87f0e30"
  },
  "#c59b93d6-2917-4560-9095-5fc7ffe4a2c7": {
    "type": "Annotation",
    "body": [
      {
        "type": "TextualBody",
        "purpose": "Transliteration",
        "dimensions": {
          "x": 767,
          "y": 1153
        },
        "value": "ki"
      },
      {
        "type": "TextualBody",
        "value": "Character",
        "purpose": "tagging"
      }
    ],
    "target": {
      "source": "https://heidicon.ub.uni-heidelberg.de/iiif/2/1125703:590047/full/full/0/default.jpg",
      "selector": {
        "type": "SvgSelector",
        "value": "<svg><polygon points=\"337.777587890625,270.358642578125 455.0655212402344,272.3465576171875 453.0776062011719,389.6344909667969 343.74139404296875,381.6827697753906\"></polygon></svg>"
      }
    },
    "@context": "http://www.w3.org/ns/anno.jsonld",
    "id": "#c59b93d6-2917-4560-9095-5fc7ffe4a2c7"
  }
}