{
  "#d6fefeab-57f8-4b06-915f-ccce13db84fb": {
    "type": "Annotation",
    "body": [
      {
        "type": "TextualBody",
        "purpose": "Transliteration",
        "value": "4(u@c)"
      },
      {
        "type": "TextualBody",
        "value": "Character",
        "purpose": "tagging"
      }
    ],
    "target": {
      "source": "https://heidicon.ub.uni-heidelberg.de/iiif/2/1125783:590137/full/full/0/default.jpg",
      "selector": {
        "type": "SvgSelector",
        "value": "<svg><polygon points=\"198.94483947753906,644.7689819335938 388.582763671875,644.7689819335938 384.1206970214844,829.9448852539062 190.0207061767578,823.2517700195312\"></polygon></svg>"
      }
    },
    "@context": "http://www.w3.org/ns/anno.jsonld",
    "id": "#d6fefeab-57f8-4b06-915f-ccce13db84fb"
  }
}